LICENSE
MANIFEST.in
README.md
ez_setup.py
setup.py
rundocker/__init__.py
rundocker/__main__.py
rundocker.egg-info/PKG-INFO
rundocker.egg-info/SOURCES.txt
rundocker.egg-info/dependency_links.txt
rundocker.egg-info/entry_points.txt
rundocker.egg-info/requires.txt
rundocker.egg-info/top_level.txt