Metadata-Version: 1.0
Name: rundocker
Version: 1.0.1
Summary: A script for running docker container process without worrying about dead container issue
Home-page: https://github.com/victorlin/rundocker
Author: Victor Lin
Author-email: hello@victorlin.me
License: UNKNOWN
Platform: UNKNOWN
